dl_with_numpy/__init__.py
dl_with_numpy/activation_functions.py
dl_with_numpy/layer.py
dl_with_numpy/linear_layer.py
dl_with_numpy/losses.py
dl_with_numpy/network.py
dl_with_numpy-0.0.3.dist-info/METADATA
dl_with_numpy-0.0.3.dist-info/RECORD
dl_with_numpy-0.0.3.dist-info/WHEEL
dl_with_numpy-0.0.3.dist-info/top_level.txt
