Metadata-Version: 2.1
Name: dl-with-numpy
Version: 0.0.3
Summary: Simple deep learning with numpy
Home-page: https://github.com/jonathan-smith-1/dl_with_numpy
Author: Jonathan Smith
Author-email: jhwsmith86@googlemail.com
License: MIT License
Platform: UNKNOWN
Classifier: Development Status :: 3 - Alpha
Classifier: Intended Audience :: Developers
Classifier: License :: OSI Approved :: MIT License
Classifier: Programming Language :: Python
Classifier: Programming Language :: Python :: 3.4
Classifier: Programming Language :: Python :: 3.5
Classifier: Programming Language :: Python :: 3.6
Requires-Dist: numpy
